{
  "configVersion": 1,
  "timestamp": 1678173210012,
  "index": "/Sam/index.html",
  "assetGroups": [
    {
      "name": "app",
      "installMode": "prefetch",
      "updateMode": "prefetch",
      "cacheQueryOptions": {
        "ignoreVary": true
      },
      "urls": [
        "/Sam/favicon.ico",
        "/Sam/index.html",
        "/Sam/main.ab65b1f590dbdee5.js",
        "/Sam/manifest.webmanifest",
        "/Sam/polyfills.ed49c418a1a5d8e2.js",
        "/Sam/runtime.f781427264c5c466.js",
        "/Sam/styles.2b4bfd22f3c7911e.css"
      ],
      "patterns": []
    },
    {
      "name": "assets",
      "installMode": "lazy",
      "updateMode": "prefetch",
      "cacheQueryOptions": {
        "ignoreVary": true
      },
      "urls": [
        "/Sam/assets/icons/icon-128x128.png",
        "/Sam/assets/icons/icon-144x144.png",
        "/Sam/assets/icons/icon-152x152.png",
        "/Sam/assets/icons/icon-192x192.png",
        "/Sam/assets/icons/icon-384x384.png",
        "/Sam/assets/icons/icon-512x512.png",
        "/Sam/assets/icons/icon-72x72.png",
        "/Sam/assets/icons/icon-96x96.png"
      ],
      "patterns": []
    }
  ],
  "dataGroups": [],
  "hashTable": {
    "/Sam/assets/icons/icon-128x128.png": "dae3b6ed49bdaf4327b92531d4b5b4a5d30c7532",
    "/Sam/assets/icons/icon-144x144.png": "b0bd89982e08f9bd2b642928f5391915b74799a7",
    "/Sam/assets/icons/icon-152x152.png": "7479a9477815dfd9668d60f8b3b2fba709b91310",
    "/Sam/assets/icons/icon-192x192.png": "1abd80d431a237a853ce38147d8c63752f10933b",
    "/Sam/assets/icons/icon-384x384.png": "329749cd6393768d3131ed6304c136b1ca05f2fd",
    "/Sam/assets/icons/icon-512x512.png": "559d9c4318b45a1f2b10596bbb4c960fe521dbcc",
    "/Sam/assets/icons/icon-72x72.png": "c457e56089a36952cd67156f9996bc4ce54a5ed9",
    "/Sam/assets/icons/icon-96x96.png": "3914125a4b445bf111c5627875fc190f560daa41",
    "/Sam/favicon.ico": "22f6a4a3bcaafafb0254e0f2fa4ceb89e505e8b2",
    "/Sam/index.html": "596cde187905c6bf35fa2d4511da31bad7ca36a5",
    "/Sam/main.ab65b1f590dbdee5.js": "be529a6182a1a7b8d4eaa9d78bc0e9003c4f7344",
    "/Sam/manifest.webmanifest": "7703584333a6f6b0a94f4e029b1469e101d3d0f2",
    "/Sam/polyfills.ed49c418a1a5d8e2.js": "b4ba1238df5613c3aa9a37a0469b16fcb1c08f1c",
    "/Sam/runtime.f781427264c5c466.js": "e1827b3fd7d144e756c82851bad0a35d66193689",
    "/Sam/styles.2b4bfd22f3c7911e.css": "17579682e360aeefa45b4788204c141cad96fa20"
  },
  "navigationUrls": [
    {
      "positive": true,
      "regex": "^\\/.*$"
    },
    {
      "positive": false,
      "regex": "^\\/(?:.+\\/)?[^/]*\\.[^/]*$"
    },
    {
      "positive": false,
      "regex": "^\\/(?:.+\\/)?[^/]*__[^/]*$"
    },
    {
      "positive": false,
      "regex": "^\\/(?:.+\\/)?[^/]*__[^/]*\\/.*$"
    }
  ],
  "navigationRequestStrategy": "performance"
}